open_karto.cpython-36m-x86_64-linux-gnu.so
.libsopen_karto/libboost_system-af73eca6.so.1.61.0
.libsopen_karto/libboost_thread-65528ca1.so.1.61.0
open_karto-1.2.3.dist-info/WHEEL
open_karto-1.2.3.dist-info/top_level.txt
open_karto-1.2.3.dist-info/METADATA
open_karto-1.2.3.dist-info/RECORD
