Metadata-Version: 2.1
Name: open-karto
Version: 1.2.3
Summary: UNKNOWN
Home-page: UNKNOWN
Author: Jariullah Safi
Author-email: safijari@isu.edu
License: UNKNOWN
Platform: UNKNOWN
Requires-Dist: pybind11 (>=2.2)
